litleparser/__init__.py
litleparser/module.py
litleparser-0.1.dist-info/LICENSE.txt
litleparser-0.1.dist-info/METADATA
litleparser-0.1.dist-info/WHEEL
litleparser-0.1.dist-info/top_level.txt
litleparser-0.1.dist-info/RECORD
